Workbook

Sheet Config_Proyectos
A1: CONFIGURACIÓN DE PROYECTOS / SOCIEDADES
A2: Un proyecto = un grupo de WhatsApp. Agregá una fila por cada sociedad/proyecto nuevo. El ID_Grupo lo completás cuando conectes el grupo en n8n (Paso 4 de la guía).
A4: ID_Proyecto | B4: Nombre_Proyecto | C4: Sociedad | D4: Grupo_WhatsApp (nombre) | E4: ID_Grupo_WhatsApp | F4: Presupuesto_Total | G4: Moneda | H4: Fecha_Inicio | I4: Activo | J4: Notas
A5: P001 | B5: Benito Juárez 4546 | C5: CIRE Fix & Flip | D5: BJ 4546 - Obra | E5: 120363xxxxxx-xxxxxxxxxx@g.us | F5: 230000 | G5: USD | H5: 2026-03-01 | I5: Sí | J5: Fondeo objetivo USD 230.000
A6: P002 | B6: Amenábar 2790 | C6: CIRE Fix & Flip | D6: Amenábar 2790 - Obra | E6: 120363yyyyyy-yyyyyyyyyy@g.us | F6: 0 | G6: USD | H6: 2025-06-01 | I6: Sí | J6: Fin de obra, en comercialización
A7: P003 | B7: Proyecto Nuevo | C7: CIRE Fix & Flip | D7: (pegar nombre grupo) | E7: (pegar ID de grupo) | F7: 0 | G7: USD | I7: No | J7: Completar al iniciar

Sheet Categorias
A1: CATEGORÍAS DE GASTO VÁLIDAS
A2: El parser de n8n valida contra esta lista. Agregar/editar categorías acá se refleja automáticamente en el bot y en el desplegable de la hoja Gastos.
A4: Categoría | B4: Palabras clave asociadas (para el parser)
A5: Materiales | B5: cemento, arena, ladrillo, hierro, caño, cable, pintura, madera
A6: Mano de Obra | B6: jornal, oficial, ayudante, cuadrilla, contratista
A7: Honorarios Profesionales | B7: arquitecto, ingeniero, gestoría, escribano, abogado
A8: Servicios | B8: luz, gas, agua, internet, seguro, alquiler equipo
A9: Impuestos y Tasas | B9: abl, ingresos brutos, tasa, municipalidad, monotributo
A10: Equipamiento | B10: herramienta, andamio, alquiler máquina, compra equipo
A11: Varios | B11: flete, comida obra, imprevisto, otros

Sheet Gastos
A1: REGISTRO MAESTRO DE GASTOS
A2: Esta hoja la completa el workflow de n8n automáticamente. No editar el orden de columnas: el bot escribe por posición de columna.
A4: ID_Gasto | B4: Fecha | C4: Hora | D4: ID_Proyecto | E4: Proyecto | F4: Categoría | G4: Monto | H4: Descripción | I4: Remitente | J4: Grupo_Origen | K4: Mensaje_Original | L4: Comprobante (foto/link) | M4: Estado | N4: Revisar
A5: G0001 | B5: 2026-07-01 | C5: 10:15 | D5: P001 | E5: =IFERROR(VLOOKUP(D5,Config_Proyectos!$A$5:$B$200,2,0),"") -> Benito Juárez 4546 | F5: Materiales | G5: 45000 | H5: Cemento y arena | I5: Juan | J5: BJ 4546 - Obra | K5: GASTO / Materiales / 45000 / Cemento y arena | M5: OK
A6: G0002 | B6: 2026-07-02 | C6: 16:40 | D6: P001 | E6: =IFERROR(VLOOKUP(D6,Config_Proyectos!$A$5:$B$200,2,0),"") -> Benito Juárez 4546 | F6: Mano de Obra | G6: 120000 | H6: Jornal cuadrilla semana | I6: Mati | J6: BJ 4546 - Obra | K6: GASTO / Mano de Obra / 120000 / Jornal cuadrilla semana | M6: OK
A7: G0003 | B7: 2026-07-03 | C7: 09:05 | D7: P001 | E7: =IFERROR(VLOOKUP(D7,Config_Proyectos!$A$5:$B$200,2,0),"") -> Benito Juárez 4546 | F7: Varios | G7: 8000 | H7: no entendí el monto, confirmar | I7: Nico | J7: BJ 4546 - Obra | K7: gasté como 8 lucas en flete | M7: Revisar | N7: Monto inferido por el parser, confirmar

Sheet Dashboard
A1: DASHBOARD DE CONTROL POR PROYECTO
A2: Se actualiza solo a partir de Gastos y Config_Proyectos. No requiere carga manual.
A4: ID_Proyecto | B4: Proyecto | C4: Presupuesto | D4: Gastado | E4: Restante | F4: % Consumido | G4: Cant. Gastos | H4: Último Gasto
A5: =IFERROR(Config_Proyectos!A5,"") -> P001 | B5: =IF(A5="","",Config_Proyectos!B5) -> Benito Juárez 4546 | C5: =IF(A5="","",Config_Proyectos!F5) -> 230000 | D5: =IF(A5="","",SUMIF(Gastos!$D$5:$D$1000,A5,Gastos!$G$5:$G$1000)) -> 173000 | E5: =IF(A5="","",C5-D5) -> 57000 | F5: =IF(OR(A5="",C5=0),"",D5/C5) -> 0.75217391 | G5: =IF(A5="","",COUNTIF(Gastos!$D$5:$D$1000,A5)) -> 3 | H5: =IF(A5="","",IFERROR(MAX(IF(Gastos!$D$5:$D$1000=A5,Gastos!$B$5:$B$1000)),"")) -> 0
A6: =IFERROR(Config_Proyectos!A6,"") -> P002 | B6: =IF(A6="","",Config_Proyectos!B6) -> Amenábar 2790 | C6: =IF(A6="","",Config_Proyectos!F6) -> 0 | D6: =IF(A6="","",SUMIF(Gastos!$D$5:$D$1000,A6,Gastos!$G$5:$G$1000)) -> 0 | E6: =IF(A6="","",C6-D6) -> 0 | F6: =IF(OR(A6="",C6=0),"",D6/C6) | G6: =IF(A6="","",COUNTIF(Gastos!$D$5:$D$1000,A6)) -> 0 | H6: =IF(A6="","",IFERROR(MAX(IF(Gastos!$D$5:$D$1000=A6,Gastos!$B$5:$B$1000)),"")) -> 0
A7: =IFERROR(Config_Proyectos!A7,"") -> P003 | B7: =IF(A7="","",Config_Proyectos!B7) -> Proyecto Nuevo | C7: =IF(A7="","",Config_Proyectos!F7) -> 0 | D7: =IF(A7="","",SUMIF(Gastos!$D$5:$D$1000,A7,Gastos!$G$5:$G$1000)) -> 0 | E7: =IF(A7="","",C7-D7) -> 0 | F7: =IF(OR(A7="",C7=0),"",D7/C7) | G7: =IF(A7="","",COUNTIF(Gastos!$D$5:$D$1000,A7)) -> 0 | H7: =IF(A7="","",IFERROR(MAX(IF(Gastos!$D$5:$D$1000=A7,Gastos!$B$5:$B$1000)),"")) -> 0
A8: =IFERROR(Config_Proyectos!A8,"") -> 0 | B8: =IF(A8="","",Config_Proyectos!B8) | C8: =IF(A8="","",Config_Proyectos!F8) | D8: =IF(A8="","",SUMIF(Gastos!$D$5:$D$1000,A8,Gastos!$G$5:$G$1000)) | E8: =IF(A8="","",C8-D8) | F8: =IF(OR(A8="",C8=0),"",D8/C8) | G8: =IF(A8="","",COUNTIF(Gastos!$D$5:$D$1000,A8)) | H8: =IF(A8="","",IFERROR(MAX(IF(Gastos!$D$5:$D$1000=A8,Gastos!$B$5:$B$1000)),""))
A9: =IFERROR(Config_Proyectos!A9,"") -> 0 | B9: =IF(A9="","",Config_Proyectos!B9) | C9: =IF(A9="","",Config_Proyectos!F9) | D9: =IF(A9="","",SUMIF(Gastos!$D$5:$D$1000,A9,Gastos!$G$5:$G$1000)) | E9: =IF(A9="","",C9-D9) | F9: =IF(OR(A9="",C9=0),"",D9/C9) | G9: =IF(A9="","",COUNTIF(Gastos!$D$5:$D$1000,A9)) | H9: =IF(A9="","",IFERROR(MAX(IF(Gastos!$D$5:$D$1000=A9,Gastos!$B$5:$B$1000)),""))
A10: =IFERROR(Config_Proyectos!A10,"") -> 0 | B10: =IF(A10="","",Config_Proyectos!B10) | C10: =IF(A10="","",Config_Proyectos!F10) | D10: =IF(A10="","",SUMIF(Gastos!$D$5:$D$1000,A10,Gastos!$G$5:$G$1000)) | E10: =IF(A10="","",C10-D10) | F10: =IF(OR(A10="",C10=0),"",D10/C10) | G10: =IF(A10="","",COUNTIF(Gastos!$D$5:$D$1000,A10)) | H10: =IF(A10="","",IFERROR(MAX(IF(Gastos!$D$5:$D$1000=A10,Gastos!$B$5:$B$1000)),""))
A11: =IFERROR(Config_Proyectos!A11,"") -> 0 | B11: =IF(A11="","",Config_Proyectos!B11) | C11: =IF(A11="","",Config_Proyectos!F11) | D11: =IF(A11="","",SUMIF(Gastos!$D$5:$D$1000,A11,Gastos!$G$5:$G$1000)) | E11: =IF(A11="","",C11-D11) | F11: =IF(OR(A11="",C11=0),"",D11/C11) | G11: =IF(A11="","",COUNTIF(Gastos!$D$5:$D$1000,A11)) | H11: =IF(A11="","",IFERROR(MAX(IF(Gastos!$D$5:$D$1000=A11,Gastos!$B$5:$B$1000)),""))
A12: =IFERROR(Config_Proyectos!A12,"") -> 0 | B12: =IF(A12="","",Config_Proyectos!B12) | C12: =IF(A12="","",Config_Proyectos!F12) | D12: =IF(A12="","",SUMIF(Gastos!$D$5:$D$1000,A12,Gastos!$G$5:$G$1000)) | E12: =IF(A12="","",C12-D12) | F12: =IF(OR(A12="",C12=0),"",D12/C12) | G12: =IF(A12="","",COUNTIF(Gastos!$D$5:$D$1000,A12)) | H12: =IF(A12="","",IFERROR(MAX(IF(Gastos!$D$5:$D$1000=A12,Gastos!$B$5:$B$1000)),""))
A13: =IFERROR(Config_Proyectos!A13,"") -> 0 | B13: =IF(A13="","",Config_Proyectos!B13) | C13: =IF(A13="","",Config_Proyectos!F13) | D13: =IF(A13="","",SUMIF(Gastos!$D$5:$D$1000,A13,Gastos!$G$5:$G$1000)) | E13: =IF(A13="","",C13-D13) | F13: =IF(OR(A13="",C13=0),"",D13/C13) | G13: =IF(A13="","",COUNTIF(Gastos!$D$5:$D$1000,A13)) | H13: =IF(A13="","",IFERROR(MAX(IF(Gastos!$D$5:$D$1000=A13,Gastos!$B$5:$B$1000)),""))
A14: =IFERROR(Config_Proyectos!A14,"") -> 0 | B14: =IF(A14="","",Config_Proyectos!B14) | C14: =IF(A14="","",Config_Proyectos!F14) | D14: =IF(A14="","",SUMIF(Gastos!$D$5:$D$1000,A14,Gastos!$G$5:$G$1000)) | E14: =IF(A14="","",C14-D14) | F14: =IF(OR(A14="",C14=0),"",D14/C14) | G14: =IF(A14="","",COUNTIF(Gastos!$D$5:$D$1000,A14)) | H14: =IF(A14="","",IFERROR(MAX(IF(Gastos!$D$5:$D$1000=A14,Gastos!$B$5:$B$1000)),""))
A15: =IFERROR(Config_Proyectos!A15,"") -> 0 | B15: =IF(A15="","",Config_Proyectos!B15) | C15: =IF(A15="","",Config_Proyectos!F15) | D15: =IF(A15="","",SUMIF(Gastos!$D$5:$D$1000,A15,Gastos!$G$5:$G$1000)) | E15: =IF(A15="","",C15-D15) | F15: =IF(OR(A15="",C15=0),"",D15/C15) | G15: =IF(A15="","",COUNTIF(Gastos!$D$5:$D$1000,A15)) | H15: =IF(A15="","",IFERROR(MAX(IF(Gastos!$D$5:$D$1000=A15,Gastos!$B$5:$B$1000)),""))
A16: =IFERROR(Config_Proyectos!A16,"") -> 0 | B16: =IF(A16="","",Config_Proyectos!B16) | C16: =IF(A16="","",Config_Proyectos!F16) | D16: =IF(A16="","",SUMIF(Gastos!$D$5:$D$1000,A16,Gastos!$G$5:$G$1000)) | E16: =IF(A16="","",C16-D16) | F16: =IF(OR(A16="",C16=0),"",D16/C16) | G16: =IF(A16="","",COUNTIF(Gastos!$D$5:$D$1000,A16)) | H16: =IF(A16="","",IFERROR(MAX(IF(Gastos!$D$5:$D$1000=A16,Gastos!$B$5:$B$1000)),""))
... A34: =IFERROR(Config_Proyectos!A34,"") -> 0 | B34: =IF(A34="","",Config_Proyectos!B34) | C34: =IF(A34="","",Config_Proyectos!F34) | D34: =IF(A34="","",SUMIF(Gastos!$D$5:$D$1000,A34,Gastos!$G$5:$G$1000)) | E34: =IF(A34="","",C34-D34) | F34: =IF(OR(A34="",C34=0),"",D34/C34) | G34: =IF(A34="","",COUNTIF(Gastos!$D$5:$D$1000,A34)) | H34: =IF(A34="","",IFERROR(MAX(IF(Gastos!$D$5:$D$1000=A34,Gastos!$B$5:$B$1000)),""))
B36: TOTAL | C36: =SUM(C5:C34) -> 230000 | D36: =SUM(D5:D34) -> 173000 | E36: =SUM(E5:E34) -> 57000

Sheet Mapeo_Grupos_Log
A1: LOG DE MENSAJES NO RECONOCIDOS
A2: Cuando un grupo de WhatsApp no tiene ID_Proyecto asignado en Config_Proyectos, o el mensaje no matchea el formato esperado, n8n escribe acá en vez de perder el dato.
A4: Fecha | B4: Hora | C4: ID_Grupo_WhatsApp | D4: Remitente | E4: Mensaje_Original | F4: Motivo
